odoo/addons/l10n_ch_partner_address_street3/README.rst
odoo/addons/l10n_ch_partner_address_street3/__init__.py
odoo/addons/l10n_ch_partner_address_street3/__manifest__.py
odoo/addons/l10n_ch_partner_address_street3/i18n/l10n_ch_partner_address_street3.pot
odoo/addons/l10n_ch_partner_address_street3/models/__init__.py
odoo/addons/l10n_ch_partner_address_street3/models/res_bank.py
odoo/addons/l10n_ch_partner_address_street3/readme/CONTRIBUTORS.rst
odoo/addons/l10n_ch_partner_address_street3/readme/DESCRIPTION.rst
odoo/addons/l10n_ch_partner_address_street3/report/swissqr_report.xml
odoo/addons/l10n_ch_partner_address_street3/static/description/icon.png
odoo/addons/l10n_ch_partner_address_street3/static/description/index.html
odoo_addon_l10n_ch_partner_address_street3-16.0.1.0.0.2.dist-info/METADATA
odoo_addon_l10n_ch_partner_address_street3-16.0.1.0.0.2.dist-info/WHEEL
odoo_addon_l10n_ch_partner_address_street3-16.0.1.0.0.2.dist-info/top_level.txt
odoo_addon_l10n_ch_partner_address_street3-16.0.1.0.0.2.dist-info/RECORD
